pip_chronos-0.1.4.dist-info/licenses/LICENSE
pipup/__init__.py
pipup/cli.py
pipup/updater.py
pip_chronos-0.1.4.dist-info/METADATA
pip_chronos-0.1.4.dist-info/WHEEL
pip_chronos-0.1.4.dist-info/entry_points.txt
pip_chronos-0.1.4.dist-info/top_level.txt
pip_chronos-0.1.4.dist-info/RECORD
