Metadata-Version: 2.4
Name: pip-chronos
Version: 0.1.4
Summary: Chronos for pip: Automatically update your requirements.txt files with the latest package versions
Author-email: Dozed Nutz <37lambada_joules@icloud.com>
License: MIT
Project-URL: Homepage, https://github.com/DeezNutzHimself/pip-chronos
Project-URL: Issues, https://github.com/DeezNutzHimself/pip-chronos/issues
Project-URL: Documentation, https://github.com/DeezNutzHimself/pip-chronos#readme
Project-URL: Changelog, https://github.com/DeezNutzHimself/pip-chronos/blob/main/CHANGELOG.md
Classifier: Development Status :: 4 - Beta
Classifier: Environment :: Console
Classifier: Intended Audience :: Developers
Classifier: License :: OSI Approved :: MIT License
Classifier: Programming Language :: Python :: 3
Classifier: Programming Language :: Python :: 3.7
Classifier: Programming Language :: Python :: 3.8
Classifier: Programming Language :: Python :: 3.9
Classifier: Programming Language :: Python :: 3.10
Classifier: Programming Language :: Python :: 3.11
Classifier: Programming Language :: Python :: 3.12
Classifier: Topic :: Software Development :: Libraries :: Python Modules
Requires-Python: >=3.7
License-File: LICENSE
Provides-Extra: dev
Requires-Dist: pytest>=7.0.0; extra == "dev"
Requires-Dist: black>=23.0.0; extra == "dev"
Requires-Dist: isort>=5.0.0; extra == "dev"
Requires-Dist: pre-commit>=3.0.0; extra == "dev"
Requires-Dist: build>=0.10.0; extra == "dev"
Requires-Dist: twine>=4.0.0; extra == "dev"
Dynamic: license-file
